py_headless_daw/__init__.py
py_headless_daw/application_container.py
py_headless_daw/compiler/__init__.py
py_headless_daw/compiler/compiler_exception.py
py_headless_daw/compiler/internal_plugin_processing_strategy_factory.py
py_headless_daw/compiler/project_compiler.py
py_headless_daw/demo/__init__.py
py_headless_daw/demo/riding_on_bugs/__init__.py
py_headless_daw/demo/riding_on_bugs/build.py
py_headless_daw/demo/riding_on_bugs/riding_on_bugs.py
py_headless_daw/dsp_utils/__init__.py
py_headless_daw/dsp_utils/adsr_envelope.py
py_headless_daw/dsp_utils/curve.py
py_headless_daw/dsp_utils/wave_producer_interface.py
py_headless_daw/dsp_utils/wave_types.py
py_headless_daw/dsp_utils/drum_synth/__init__.py
py_headless_daw/dsp_utils/drum_synth/drum_synth_config_factory.py
py_headless_daw/dsp_utils/drum_synth/drum_synth_generator.py
py_headless_daw/dsp_utils/drum_synth/drum_synth_generator_config.py
py_headless_daw/dsp_utils/drum_synth/one_shot_oscillator.py
py_headless_daw/dto/__init__.py
py_headless_daw/dto/waveform.py
py_headless_daw/integrations/__init__.py
py_headless_daw/integrations/amsynth/__init__.py
py_headless_daw/integrations/amsynth/amsynth_parameter_normalizer.py
py_headless_daw/processing/__init__.py
py_headless_daw/processing/event/__init__.py
py_headless_daw/processing/event/midi_track_strategy.py
py_headless_daw/processing/event/value_provider_based_event_emitter.py
py_headless_daw/processing/hybrid/__init__.py
py_headless_daw/processing/hybrid/drum_synth_strategy.py
py_headless_daw/processing/hybrid/transparent_strategy.py
py_headless_daw/processing/hybrid/vst_plugin.py
py_headless_daw/processing/stream/__init__.py
py_headless_daw/processing/stream/constant_level.py
py_headless_daw/processing/stream/impulse_noice_generator.py
py_headless_daw/processing/stream/mixer.py
py_headless_daw/processing/stream/sampler.py
py_headless_daw/processing/stream/stereo_panner.py
py_headless_daw/processing/stream/stream_gain.py
py_headless_daw/production/__init__.py
py_headless_daw-0.0.5.dist-info/LICENSE
py_headless_daw-0.0.5.dist-info/METADATA
py_headless_daw-0.0.5.dist-info/WHEEL
py_headless_daw-0.0.5.dist-info/top_level.txt
py_headless_daw-0.0.5.dist-info/RECORD
