Metadata-Version: 2.1
Name: py-headless-daw
Version: 0.0.5
Summary: A GUI-less DAW (Digital Audio Workstation) for producing electronic music using python
Home-page: https://github.com/hq9000/py_headless_daw
Author: Sergey Grechin
Author-email: grechin.sergey@gmail.com
License: UNKNOWN
Platform: UNKNOWN
Classifier: Programming Language :: Python :: 3
Classifier: License :: OSI Approved :: MIT License
Classifier: Operating System :: OS Independent
Requires-Python: >=3.7
Requires-Dist: numpy
Requires-Dist: cython-vst-loader
Requires-Dist: dependency-injector
Requires-Dist: scipy
